jogodavelhagenetico/__init__.py
jogodavelhagenetico/arvorejogodavelha.py
jogodavelhagenetico/ferramentas.py
jogodavelhagenetico/geradordearvore.py
jogodavelhagenetico/jogadorgenetico.py
jogodavelhagenetico/modelos.py
jogodavelhagenetico/parametros.py
jogodavelhagenetico/treinamento.py
jogodavelhagenetico/modelo/arvorejvelha.pkl
jogodavelhagenetico/modelo/populacao_o.npy
jogodavelhagenetico/modelo/populacao_p_o.npy
jogodavelhagenetico/modelo/populacao_p_x.npy
jogodavelhagenetico/modelo/populacao_x.npy
velhaapp/__init__.py
velhaapp/__main__.py
velhaapp/controle.py
velhaapp/jogadores.py
velhaapp/tela.py
jogodavelhagenetico-0.1.0.dist-info/METADATA
jogodavelhagenetico-0.1.0.dist-info/WHEEL
jogodavelhagenetico-0.1.0.dist-info/entry_points.txt
jogodavelhagenetico-0.1.0.dist-info/top_level.txt
jogodavelhagenetico-0.1.0.dist-info/RECORD
