Metadata-Version: 2.1
Name: jogodavelhagenetico
Version: 0.1.0
Summary: Genetic Algorithm to play tic tac toe
Home-page: https://github.com/duducosmos/jogodavelhagenetico
Author: Eduardo S. Pereira
Author-email: pereira.somoza@gmail.com
License: Apache License 2.0
Platform: UNKNOWN
Requires-Dist: numpy
Requires-Dist: pathos
Requires-Dist: matplotlib
Requires-Dist: pygenec
